discordPyExt/__init__.py
discordPyExt/components/__init__.py
discordPyExt/components/botx.py
discordPyExt/components/cogx.py
discordPyExt/components/ctxx.py
discordPyExt/components/embedX.py
discordPyExt/components/text.py
discordPyExt/ext/__init__.py
discordPyExt/ext/data.py
discordPyExt/ext/storage.py
discordPyExt/ext/testCase.py
discordPyExt/interfaces/embedColor.py
discordPyExt/setup/__init__.py
discordPyExt/setup/deploy.py
discordPyExt/setup/extension.py
discordPyExt/setup/interface.py
discordPyExt/setup/ext/__init__.py
discordPyExt/setup/ext/bot.py
discordPyExt/setup/ext/flask.py
discordPyExt/setup/ext/flaskColdTrigger.py
discordPyExt/setup/ext/flaskSqlalchemy.py
discordPyExt/utils/dc.py
discordPyExt/utils/deploy.py
discordPyExt/utils/doNothing.py
discordPyExt/utils/misc.py
discordPyExt/utils/str.py
DiscordPyExt-0.0.3.dist-info/LICENSE
DiscordPyExt-0.0.3.dist-info/METADATA
DiscordPyExt-0.0.3.dist-info/WHEEL
DiscordPyExt-0.0.3.dist-info/entry_points.txt
DiscordPyExt-0.0.3.dist-info/top_level.txt
DiscordPyExt-0.0.3.dist-info/RECORD
