Metadata-Version: 2.1
Name: DiscordPyExt
Version: 0.0.3
Summary: extended utilities for discord.py
Home-page: https://www.github.com/ZackaryW/discordPyExt
Author: Zackary W
Classifier: Programming Language :: Python :: 3
Classifier: License :: OSI Approved :: MIT License
Classifier: Operating System :: OS Independent
Classifier: Development Status :: 3 - Alpha
Classifier: Intended Audience :: Developers
Requires-Python: >=3.6
License-File: LICENSE
Requires-Dist: discord.py
Requires-Dist: pydantic
Provides-Extra: deploy
Requires-Dist: flask ; extra == 'deploy'
Requires-Dist: flask-sqlalchemy ; extra == 'deploy'
